{
  "string": [
    {
      "name": "module_desc",
      "value": "module description"
    },
    {
      "name": "EntryAbility_desc",
      "value": "description"
    },
    {
      "name": "EntryAbility_label",
      "value": "label"
    },
    {
      "name": "login_text",
      "value": "登录"
    },
    {
      "name": "my_love",
      "value": "我的最爱"
    },
    {
      "name": "history_record",
      "value": "历史记录"
    },
    {
      "name": "message",
      "value": "消息"
    },
    {
      "name": "shopping_cart",
      "value": "购物车"
    },
    {
      "name": "my_goal",
      "value": "我的目标"
    },
    {
      "name": "group",
      "value": "圈子"
    },
    {
      "name": "favorites",
      "value": "收藏"
    },
    {
      "name": "recycle_bin",
      "value": "回收站"
    },
    {
      "name": "rankings",
      "value": "排行榜"
    },
    {
      "name": "mainPage_text_top",
      "value": "厦门站，我们不见不散"
    },
    {
      "name": "mainPage_new",
      "value": "新品首发"
    },
    {
      "name": "mainPage_text_new",
      "value": "厦门站，我们不见不散"
    },
    {
      "name": "mainPage_brand",
      "value": "大牌闪购"
    },
    {
      "name": "mainPage_text_brand",
      "value": "更多大牌"
    },
    {
      "name": "mainPage_found",
      "value": "发现好物"
    },
    {
      "name": "mainPage_text_found",
      "value": "厦门站，我们不见不散"
    },
    {
      "name": "mainPage_top",
      "value": "排行榜"
    }
  ]
}